[
  {
    "id": 1,
    "title": "Standard com vista para a Baía Sul",
    "image": [
      "/img/rooms/standard-com-vista/01.png",
      "/img/rooms/standard-com-vista/02.png",
      "/img/rooms/standard-com-vista/03.png",
      "/img/rooms/standard-com-vista/04.png",
      "/img/rooms/standard-com-vista/05.png",
      "/img/rooms/standard-com-vista/06.png",
      "/img/rooms/standard-com-vista/07.png"
    ],
    "description": "Procura preço baixo, mas não quer perder o encanto do pôr do sol e o visual deslumbrante da Baía Sul? Escolha uma dessas opções!",
    "benefits": [
      "Ar-condicionado Quente e Frio",
      "Ventilador de teto",
      "TV tela plana com canais locais",
      "Wi-fi",
      "Mesa de trabalho",
      "Frigobar",
      "Cofre",
      "Banheiro privativo",
      "Vista de frente da Baía Sul e Ponte",
      "Com sacada ou varanda"
    ],
    "hospeds": 4,
    "beds": "Cama casal + Cama solteiro + Cama Baixa OU 04 camas de solteiro (uma baixa)"
  },
  {
    "id": 2,
    "title": "Standard sem vista para a Baía Sul",
    "image": [
      "/img/rooms/standard-sem-vista/01.png",
      "/img/rooms/standard-sem-vista/02.png",
      "/img/rooms/standard-sem-vista/03.png",
      "/img/rooms/standard-sem-vista/04.png",
      "/img/rooms/standard-sem-vista/05.png",
      "/img/rooms/standard-sem-vista/06.png"
    ],
    "description": "Quer economizar? Veja nossas melhores opções para hospedagens curtas e economicas",
    "benefits": [
      "Ar-condicionado Quente e Frio",
      "Ventilador de teto",
      "TV tela plana com canais locais",
      "Wi-fi",
      "Mesa de trabalho",
      "Frigobar",
      "Cofre",
      "Banheiro privativo",
      "Sem sacada"
    ],
    "hospeds": 3,
    "beds": "Cama casal + Cama solteiro OU 03 camas de solteiro"
  },
  {
    "id": 3,
    "title": "Standard com vista parcial da Baía Sul",
    "image": [
      "/img/rooms/standard-com-vista-parcial/01.png",
      "/img/rooms/standard-com-vista-parcial/02.png",
      "/img/rooms/standard-com-vista-parcial/03.png",
      "/img/rooms/standard-com-vista-parcial/04.png",
      "/img/rooms/standard-com-vista-parcial/05.png",
      "/img/rooms/standard-com-vista-parcial/06.png"
    ],
    "description": "Procura preço baixo, mas não quer perder o encanto do pôr do sol e o visual deslumbrante da Baía Sul? Escolha uma dessas opções!",
    "benefits": [
      "Ar-condicionado Quente e Frio",
      "Ventilador de teto",
      "TV tela plana com canais locais",
      "Wi-fi",
      "Mesa de trabalho",
      "Frigobar",
      "Cofre",
      "Banheiro privativo",
      "Sem sacada",
      "Vista lateral da Baía Sul e Ponte"
    ],
    "hospeds": 3,
    "beds": "Cama casal + Cama solteiro OU 03 camas de solteiro"
  },
  {
    "id": 5,
    "title": "Quarto superior com vista e hidromassagem single",
    "image": [
      "/img/rooms/superior-hidro-single/01.png",
      "/img/rooms/superior-hidro-single/02.png",
      "/img/rooms/superior-hidro-single/03.png",
      "/img/rooms/superior-hidro-single/04.png",
      "/img/rooms/superior-hidro-single/05.png",
      "/img/rooms/superior-hidro-single/06.png",
      "/img/rooms/superior-hidro-single/07.png"
    ],
    "description": "Quer se hospedar sem abrir mão do conforto e de comodidades especiais? Nosso quartos com hidromassagem são a escolha certa!",
    "benefits": [
      "Ar-condicionado Quente e Frio",
      "Ventilador de teto",
      "TV tela plana com canais locais",
      "Wi-fi",
      "Mesa de trabalho",
      "Frigobar",
      "Cofre",
      "Banheiro privativo",
      "Vista de frente da Baía Sul e Ponte",
      "Hidromassagem tamanho individual",
      "Com sacada ou varanda"
    ],
    "hospeds": 3,
    "beds": "Cama casal + Cama Baixa"
  },
  {
    "id": 4,
    "title": "Quarto deluxe com vista e hidromassagem dupla",
    "image": [
      "/img/rooms/deluxe-hidro-dupla/01.png",
      "/img/rooms/deluxe-hidro-dupla/02.png",
      "/img/rooms/deluxe-hidro-dupla/03.png",
      "/img/rooms/deluxe-hidro-dupla/04.png",
      "/img/rooms/deluxe-hidro-dupla/05.png",
      "/img/rooms/deluxe-hidro-dupla/06.png",
      "/img/rooms/deluxe-hidro-dupla/07.png",
      "/img/rooms/deluxe-hidro-dupla/08.png"
    ],
    "description": "Quer se hospedar sem abrir mão do conforto e de comodidades especiais? Nosso quartos com hidromassagem são a escolha certa!",
    "benefits": [
      "Ar-condicionado Quente e Frio",
      "Ventilador de teto",
      "TV tela plana com canais locais",
      "Wi-fi",
      "Mesa de trabalho",
      "Frigobar",
      "Cofre",
      "Banheiro privativo",
      "Vista de frente da Baía Sul e Ponte",
      "Hidromassagem tamanho dupla",
      "Com sacada ou varanda"
    ],
    "hospeds": 3,
    "beds": "Cama casal + Cama Baixa"
  }
]
